<?xml version="1.0"?>
<AEI_Report xmlns:xsd="http://www.w3.org/2001/XMLSchema" xmlns:xsi="http://www.w3.org/2001/XMLSchema-instance">
  <scannername>Detector 328.6_0</scannername>
  <trainsymbol>Z-STOWSP6-15</trainsymbol>
  <trainspeedmph>043</trainspeedmph>
  <totalaxles>236</totalaxles>
  <totalloads>53</totalloads>
  <totalmtys>0</totalmtys>
  <totaltons>5136</totaltons>
  <trainlengthft>4918</trainlengthft>
  <reportdata>
    <AEI_Report_UnitData>
      <equipmentype>Loco</equipmentype>
      <direction>Fwd</direction>
      <sequence />
      <roadname>RUNW</roadname>
      <unitnumber>9620</unitnumber>
      <isloaded>true</isloaded>
      <cargotons>11</cargotons>
      <hazmatPlacardIndex>0</hazmatPlacardIndex>
      <destinationtag />
      <cardefect>All_Ok</cardefect>
      <carfilename>R8_C449W_Run801.xml</carfilename>
    </AEI_Report_UnitData>
    <AEI_Report_UnitData>
      <equipmentype>Loco</equipmentype>
      <direction>Fwd</direction>
      <sequence />
      <roadname>RUNW</roadname>
      <unitnumber>9622</unitnumber>
      <isloaded>true</isloaded>
      <cargotons>11</cargotons>
      <hazmatPlacardIndex>0</hazmatPlacardIndex>
      <destinationtag />
      <cardefect>All_Ok</cardefect>
      <carfilename>R8_C449W_Run801.xml</carfilename>
    </AEI_Report_UnitData>
    <AEI_Report_UnitData>
      <equipmentype>Loco</equipmentype>
      <direction>Fwd</direction>
      <sequence />
      <roadname>RUNW</roadname>
      <unitnumber>9608</unitnumber>
      <isloaded>true</isloaded>
      <cargotons>9</cargotons>
      <hazmatPlacardIndex>0</hazmatPlacardIndex>
      <destinationtag />
      <cardefect>All_Ok</cardefect>
      <carfilename>R8_C449W_Run801.xml</carfilename>
    </AEI_Report_UnitData>
    <AEI_Report_UnitData>
      <equipmentype>Loco</equipmentype>
      <direction>Fwd</direction>
      <sequence />
      <roadname>RUNW</roadname>
      <unitnumber>9684</unitnumber>
      <isloaded>true</isloaded>
      <cargotons>6</cargotons>
      <hazmatPlacardIndex>0</hazmatPlacardIndex>
      <destinationtag />
      <cardefect>All_Ok</cardefect>
      <carfilename>R8_C449W_Run801.xml</carfilename>
    </AEI_Report_UnitData>
    <AEI_Report_UnitData>
      <equipmentype>Well</equipmentype>
      <direction>Rev</direction>
      <sequence>001</sequence>
      <roadname>DTTX</roadname>
      <unitnumber>344483</unitnumber>
      <isloaded>true</isloaded>
      <cargotons>88</cargotons>
      <hazmatPlacardIndex>0</hazmatPlacardIndex>
      <destinationtag>WSP</destinationtag>
      <cardefect>All_Ok</cardefect>
      <carfilename>Run8_WellCar53_DTTX01.xml</carfilename>
    </AEI_Report_UnitData>
    <AEI_Report_UnitData>
      <equipmentype>Well</equipmentype>
      <direction>Fwd</direction>
      <sequence>002</sequence>
      <roadname>DTTX</roadname>
      <unitnumber>400977</unitnumber>
      <isloaded>true</isloaded>
      <cargotons>88</cargotons>
      <hazmatPlacardIndex>0</hazmatPlacardIndex>
      <destinationtag>WSP</destinationtag>
      <cardefect>All_Ok</cardefect>
      <carfilename>Run8_WellCar53_DTTX01.xml</carfilename>
    </AEI_Report_UnitData>
    <AEI_Report_UnitData>
      <equipmentype>Well</equipmentype>
      <direction>Rev</direction>
      <sequence>003</sequence>
      <roadname>FEC</roadname>
      <unitnumber>722506</unitnumber>
      <isloaded>true</isloaded>
      <cargotons>88</cargotons>
      <hazmatPlacardIndex>0</hazmatPlacardIndex>
      <destinationtag>WSP</destinationtag>
      <cardefect>All_Ok</cardefect>
      <carfilename>Run8_WellCar53AP_FEC16.xml</carfilename>
    </AEI_Report_UnitData>
    <AEI_Report_UnitData>
      <equipmentype>Well</equipmentype>
      <direction>Fwd</direction>
      <sequence>004</sequence>
      <roadname>FEC</roadname>
      <unitnumber>976027</unitnumber>
      <isloaded>true</isloaded>
      <cargotons>88</cargotons>
      <hazmatPlacardIndex>0</hazmatPlacardIndex>
      <destinationtag>WSP</destinationtag>
      <cardefect>All_Ok</cardefect>
      <carfilename>Run8_WellCar53AP_FEC16.xml</carfilename>
    </AEI_Report_UnitData>
    <AEI_Report_UnitData>
      <equipmentype>Well</equipmentype>
      <direction>Fwd</direction>
      <sequence>005</sequence>
      <roadname>DTTX</roadname>
      <unitnumber>536400</unitnumber>
      <isloaded>true</isloaded>
      <cargotons>33</cargotons>
      <hazmatPlacardIndex>0</hazmatPlacardIndex>
      <destinationtag>WSP</destinationtag>
      <cardefect>All_Ok</cardefect>
      <carfilename>Run8_52ftwell_1Schneider.xml</carfilename>
    </AEI_Report_UnitData>
    <AEI_Report_UnitData>
      <equipmentype>Well</equipmentype>
      <direction>Rev</direction>
      <sequence>006</sequence>
      <roadname>FEC</roadname>
      <unitnumber>360213</unitnumber>
      <isloaded>true</isloaded>
      <cargotons>88</cargotons>
      <hazmatPlacardIndex>0</hazmatPlacardIndex>
      <destinationtag>WSP</destinationtag>
      <cardefect>All_Ok</cardefect>
      <carfilename>Run8_WellCar53AP_FEC16.xml</carfilename>
    </AEI_Report_UnitData>
    <AEI_Report_UnitData>
      <equipmentype>Well</equipmentype>
      <direction>Fwd</direction>
      <sequence>007</sequence>
      <roadname>FEC</roadname>
      <unitnumber>282487</unitnumber>
      <isloaded>true</isloaded>
      <cargotons>88</cargotons>
      <hazmatPlacardIndex>0</hazmatPlacardIndex>
      <destinationtag>WSP</destinationtag>
      <cardefect>All_Ok</cardefect>
      <carfilename>Run8_WellCar53AP_FEC16.xml</carfilename>
    </AEI_Report_UnitData>
    <AEI_Report_UnitData>
      <equipmentype>Well</equipmentype>
      <direction>Fwd</direction>
      <sequence>008</sequence>
      <roadname>DTTX</roadname>
      <unitnumber>909730</unitnumber>
      <isloaded>true</isloaded>
      <cargotons>88</cargotons>
      <hazmatPlacardIndex>0</hazmatPlacardIndex>
      <destinationtag>WSP</destinationtag>
      <cardefect>All_Ok</cardefect>
      <carfilename>Run8_WellCar53_DTTX01.xml</carfilename>
    </AEI_Report_UnitData>
    <AEI_Report_UnitData>
      <equipmentype>Well</equipmentype>
      <direction>Rev</direction>
      <sequence>009</sequence>
      <roadname>DTTX</roadname>
      <unitnumber>735197</unitnumber>
      <isloaded>true</isloaded>
      <cargotons>33</cargotons>
      <hazmatPlacardIndex>0</hazmatPlacardIndex>
      <destinationtag>WSP</destinationtag>
      <cardefect>All_Ok</cardefect>
      <carfilename>Run8_52ftwell_1Schneider.xml</carfilename>
    </AEI_Report_UnitData>
    <AEI_Report_UnitData>
      <equipmentype>Reefer</equipmentype>
      <direction>Rev</direction>
      <sequence>010</sequence>
      <roadname>ARMN</roadname>
      <unitnumber>649599</unitnumber>
      <isloaded>true</isloaded>
      <cargotons>97</cargotons>
      <hazmatPlacardIndex>0</hazmatPlacardIndex>
      <destinationtag>WSP</destinationtag>
      <cardefect>All_Ok</cardefect>
      <carfilename>R8_Reefer_TrinCool_64_ARMN.xml</carfilename>
    </AEI_Report_UnitData>
    <AEI_Report_UnitData>
      <equipmentype>Reefer</equipmentype>
      <direction>Rev</direction>
      <sequence>011</sequence>
      <roadname>BNSF</roadname>
      <unitnumber>333798</unitnumber>
      <isloaded>true</isloaded>
      <cargotons>90</cargotons>
      <hazmatPlacardIndex>0</hazmatPlacardIndex>
      <destinationtag>WSP</destinationtag>
      <cardefect>All_Ok</cardefect>
      <carfilename>R8_Reefer_TrinCool_72_BNSF.xml</carfilename>
    </AEI_Report_UnitData>
    <AEI_Report_UnitData>
      <equipmentype>Reefer</equipmentype>
      <direction>Rev</direction>
      <sequence>012</sequence>
      <roadname>ARMN</roadname>
      <unitnumber>463610</unitnumber>
      <isloaded>true</isloaded>
      <cargotons>97</cargotons>
      <hazmatPlacardIndex>0</hazmatPlacardIndex>
      <destinationtag>WSP</destinationtag>
      <cardefect>All_Ok</cardefect>
      <carfilename>R8_Reefer_TrinCool_64_ARMN.xml</carfilename>
    </AEI_Report_UnitData>
    <AEI_Report_UnitData>
      <equipmentype>Reefer</equipmentype>
      <direction>Fwd</direction>
      <sequence>013</sequence>
      <roadname>CRYX</roadname>
      <unitnumber>335479</unitnumber>
      <isloaded>true</isloaded>
      <cargotons>92</cargotons>
      <hazmatPlacardIndex>0</hazmatPlacardIndex>
      <destinationtag>WSP</destinationtag>
      <cardefect>All_Ok</cardefect>
      <carfilename>R8_Reefer_Greenbrier_72_CRYX.xml</carfilename>
    </AEI_Report_UnitData>
    <AEI_Report_UnitData>
      <equipmentype>Reefer</equipmentype>
      <direction>Fwd</direction>
      <sequence>014</sequence>
      <roadname>BNSF</roadname>
      <unitnumber>946202</unitnumber>
      <isloaded>true</isloaded>
      <cargotons>90</cargotons>
      <hazmatPlacardIndex>0</hazmatPlacardIndex>
      <destinationtag>WSP</destinationtag>
      <cardefect>All_Ok</cardefect>
      <carfilename>R8_Reefer_TrinCool_72_BNSF.xml</carfilename>
    </AEI_Report_UnitData>
    <AEI_Report_UnitData>
      <equipmentype>Reefer</equipmentype>
      <direction>Fwd</direction>
      <sequence>015</sequence>
      <roadname>TPIX</roadname>
      <unitnumber>692893</unitnumber>
      <isloaded>true</isloaded>
      <cargotons>94</cargotons>
      <hazmatPlacardIndex>0</hazmatPlacardIndex>
      <destinationtag>WSP</destinationtag>
      <cardefect>All_Ok</cardefect>
      <carfilename>R8_Reefer_Millenium_64_TPIX.xml</carfilename>
    </AEI_Report_UnitData>
    <AEI_Report_UnitData>
      <equipmentype>Reefer</equipmentype>
      <direction>Fwd</direction>
      <sequence>016</sequence>
      <roadname>TPIX</roadname>
      <unitnumber>668416</unitnumber>
      <isloaded>true</isloaded>
      <cargotons>94</cargotons>
      <hazmatPlacardIndex>0</hazmatPlacardIndex>
      <destinationtag>WSP</destinationtag>
      <cardefect>All_Ok</cardefect>
      <carfilename>R8_Reefer_Millenium_64_TPIX.xml</carfilename>
    </AEI_Report_UnitData>
    <AEI_Report_UnitData>
      <equipmentype>Reefer</equipmentype>
      <direction>Rev</direction>
      <sequence>017</sequence>
      <roadname>ARMN</roadname>
      <unitnumber>534587</unitnumber>
      <isloaded>true</isloaded>
      <cargotons>97</cargotons>
      <hazmatPlacardIndex>0</hazmatPlacardIndex>
      <destinationtag>WSP</destinationtag>
      <cardefect>All_Ok</cardefect>
      <carfilename>R8_Reefer_TrinCool_64_ARMN.xml</carfilename>
    </AEI_Report_UnitData>
    <AEI_Report_UnitData>
      <equipmentype>Reefer</equipmentype>
      <direction>Rev</direction>
      <sequence>018</sequence>
      <roadname>ARMN</roadname>
      <unitnumber>761685</unitnumber>
      <isloaded>true</isloaded>
      <cargotons>97</cargotons>
      <hazmatPlacardIndex>0</hazmatPlacardIndex>
      <destinationtag>WSP</destinationtag>
      <cardefect>All_Ok</cardefect>
      <carfilename>R8_Reefer_TrinCool_64_ARMN.xml</carfilename>
    </AEI_Report_UnitData>
    <AEI_Report_UnitData>
      <equipmentype>Reefer</equipmentype>
      <direction>Rev</direction>
      <sequence>019</sequence>
      <roadname>TPIX</roadname>
      <unitnumber>866852</unitnumber>
      <isloaded>true</isloaded>
      <cargotons>94</cargotons>
      <hazmatPlacardIndex>0</hazmatPlacardIndex>
      <destinationtag>WSP</destinationtag>
      <cardefect>All_Ok</cardefect>
      <carfilename>R8_Reefer_Millenium_64_TPIX.xml</carfilename>
    </AEI_Report_UnitData>
    <AEI_Report_UnitData>
      <equipmentype>Reefer</equipmentype>
      <direction>Rev</direction>
      <sequence>020</sequence>
      <roadname>CRYX</roadname>
      <unitnumber>935982</unitnumber>
      <isloaded>true</isloaded>
      <cargotons>92</cargotons>
      <hazmatPlacardIndex>0</hazmatPlacardIndex>
      <destinationtag>WSP</destinationtag>
      <cardefect>All_Ok</cardefect>
      <carfilename>R8_Reefer_Greenbrier_72_CRYX.xml</carfilename>
    </AEI_Report_UnitData>
    <AEI_Report_UnitData>
      <equipmentype>Piggyback</equipmentype>
      <direction>Rev</direction>
      <sequence>021</sequence>
      <roadname>RTTX</roadname>
      <unitnumber>430679</unitnumber>
      <isloaded>true</isloaded>
      <cargotons>45</cargotons>
      <hazmatPlacardIndex>0</hazmatPlacardIndex>
      <destinationtag>WSP</destinationtag>
      <cardefect>All_Ok</cardefect>
      <carfilename>R8_Pig_RTTX04.xml</carfilename>
    </AEI_Report_UnitData>
    <AEI_Report_UnitData>
      <equipmentype>Piggyback</equipmentype>
      <direction>Rev</direction>
      <sequence>022</sequence>
      <roadname>RTTX</roadname>
      <unitnumber>645396</unitnumber>
      <isloaded>true</isloaded>
      <cargotons>45</cargotons>
      <hazmatPlacardIndex>0</hazmatPlacardIndex>
      <destinationtag>WSP</destinationtag>
      <cardefect>All_Ok</cardefect>
      <carfilename>R8_Pig_RTTX05.xml</carfilename>
    </AEI_Report_UnitData>
    <AEI_Report_UnitData>
      <equipmentype>Piggyback</equipmentype>
      <direction>Fwd</direction>
      <sequence>023</sequence>
      <roadname>RTTX</roadname>
      <unitnumber>788858</unitnumber>
      <isloaded>true</isloaded>
      <cargotons>45</cargotons>
      <hazmatPlacardIndex>0</hazmatPlacardIndex>
      <destinationtag>WSP</destinationtag>
      <cardefect>All_Ok</cardefect>
      <carfilename>R8_Pig_RTTX03.xml</carfilename>
    </AEI_Report_UnitData>
    <AEI_Report_UnitData>
      <equipmentype>Piggyback</equipmentype>
      <direction>Rev</direction>
      <sequence>024</sequence>
      <roadname>RTTX</roadname>
      <unitnumber>682889</unitnumber>
      <isloaded>true</isloaded>
      <cargotons>45</cargotons>
      <hazmatPlacardIndex>0</hazmatPlacardIndex>
      <destinationtag>WSP</destinationtag>
      <cardefect>All_Ok</cardefect>
      <carfilename>R8_Pig_RTTX06.xml</carfilename>
    </AEI_Report_UnitData>
    <AEI_Report_UnitData>
      <equipmentype>Piggyback</equipmentype>
      <direction>Fwd</direction>
      <sequence>025</sequence>
      <roadname>RTTX</roadname>
      <unitnumber>970735</unitnumber>
      <isloaded>true</isloaded>
      <cargotons>45</cargotons>
      <hazmatPlacardIndex>0</hazmatPlacardIndex>
      <destinationtag>WSP</destinationtag>
      <cardefect>All_Ok</cardefect>
      <carfilename>R8_Pig_RTTX04.xml</carfilename>
    </AEI_Report_UnitData>
    <AEI_Report_UnitData>
      <equipmentype>Piggyback</equipmentype>
      <direction>Fwd</direction>
      <sequence>026</sequence>
      <roadname>RTTX</roadname>
      <unitnumber>702617</unitnumber>
      <isloaded>true</isloaded>
      <cargotons>45</cargotons>
      <hazmatPlacardIndex>0</hazmatPlacardIndex>
      <destinationtag>WSP</destinationtag>
      <cardefect>All_Ok</cardefect>
      <carfilename>R8_Pig_RTTX05.xml</carfilename>
    </AEI_Report_UnitData>
    <AEI_Report_UnitData>
      <equipmentype>Piggyback</equipmentype>
      <direction>Rev</direction>
      <sequence>027</sequence>
      <roadname>RTTX</roadname>
      <unitnumber>907945</unitnumber>
      <isloaded>true</isloaded>
      <cargotons>45</cargotons>
      <hazmatPlacardIndex>0</hazmatPlacardIndex>
      <destinationtag>WSP</destinationtag>
      <cardefect>All_Ok</cardefect>
      <carfilename>R8_Pig_RTTX04.xml</carfilename>
    </AEI_Report_UnitData>
    <AEI_Report_UnitData>
      <equipmentype>Piggyback</equipmentype>
      <direction>Rev</direction>
      <sequence>028</sequence>
      <roadname>RTTX</roadname>
      <unitnumber>204930</unitnumber>
      <isloaded>true</isloaded>
      <cargotons>45</cargotons>
      <hazmatPlacardIndex>0</hazmatPlacardIndex>
      <destinationtag>WSP</destinationtag>
      <cardefect>All_Ok</cardefect>
      <carfilename>R8_Pig_RTTX07.xml</carfilename>
    </AEI_Report_UnitData>
    <AEI_Report_UnitData>
      <equipmentype>Piggyback</equipmentype>
      <direction>Fwd</direction>
      <sequence>029</sequence>
      <roadname>RTTX</roadname>
      <unitnumber>360166</unitnumber>
      <isloaded>true</isloaded>
      <cargotons>45</cargotons>
      <hazmatPlacardIndex>0</hazmatPlacardIndex>
      <destinationtag>WSP</destinationtag>
      <cardefect>All_Ok</cardefect>
      <carfilename>R8_Pig_RTTX01.xml</carfilename>
    </AEI_Report_UnitData>
    <AEI_Report_UnitData>
      <equipmentype>Piggyback</equipmentype>
      <direction>Fwd</direction>
      <sequence>030</sequence>
      <roadname>RTTX</roadname>
      <unitnumber>258966</unitnumber>
      <isloaded>true</isloaded>
      <cargotons>45</cargotons>
      <hazmatPlacardIndex>0</hazmatPlacardIndex>
      <destinationtag>WSP</destinationtag>
      <cardefect>All_Ok</cardefect>
      <carfilename>R8_Pig_RTTX07.xml</carfilename>
    </AEI_Report_UnitData>
    <AEI_Report_UnitData>
      <equipmentype>Piggyback</equipmentype>
      <direction>Fwd</direction>
      <sequence>031</sequence>
      <roadname>RTTX</roadname>
      <unitnumber>103836</unitnumber>
      <isloaded>true</isloaded>
      <cargotons>45</cargotons>
      <hazmatPlacardIndex>0</hazmatPlacardIndex>
      <destinationtag>WSP</destinationtag>
      <cardefect>All_Ok</cardefect>
      <carfilename>R8_Pig_RTTX04.xml</carfilename>
    </AEI_Report_UnitData>
    <AEI_Report_UnitData>
      <equipmentype>Piggyback</equipmentype>
      <direction>Fwd</direction>
      <sequence>032</sequence>
      <roadname>RTTX</roadname>
      <unitnumber>642747</unitnumber>
      <isloaded>true</isloaded>
      <cargotons>45</cargotons>
      <hazmatPlacardIndex>0</hazmatPlacardIndex>
      <destinationtag>WSP</destinationtag>
      <cardefect>All_Ok</cardefect>
      <carfilename>R8_Pig_RTTX07.xml</carfilename>
    </AEI_Report_UnitData>
    <AEI_Report_UnitData>
      <equipmentype>Piggyback</equipmentype>
      <direction>Rev</direction>
      <sequence>033</sequence>
      <roadname>RTTX</roadname>
      <unitnumber>427157</unitnumber>
      <isloaded>true</isloaded>
      <cargotons>45</cargotons>
      <hazmatPlacardIndex>0</hazmatPlacardIndex>
      <destinationtag>WSP</destinationtag>
      <cardefect>All_Ok</cardefect>
      <carfilename>R8_Pig_RTTX03.xml</carfilename>
    </AEI_Report_UnitData>
    <AEI_Report_UnitData>
      <equipmentype>Piggyback</equipmentype>
      <direction>Fwd</direction>
      <sequence>034</sequence>
      <roadname>RTTX</roadname>
      <unitnumber>487010</unitnumber>
      <isloaded>true</isloaded>
      <cargotons>45</cargotons>
      <hazmatPlacardIndex>0</hazmatPlacardIndex>
      <destinationtag>WSP</destinationtag>
      <cardefect>All_Ok</cardefect>
      <carfilename>R8_Pig_RTTX02.xml</carfilename>
    </AEI_Report_UnitData>
    <AEI_Report_UnitData>
      <equipmentype>Piggyback</equipmentype>
      <direction>Fwd</direction>
      <sequence>035</sequence>
      <roadname>RTTX</roadname>
      <unitnumber>991926</unitnumber>
      <isloaded>true</isloaded>
      <cargotons>45</cargotons>
      <hazmatPlacardIndex>0</hazmatPlacardIndex>
      <destinationtag>WSP</destinationtag>
      <cardefect>All_Ok</cardefect>
      <carfilename>R8_Pig_RTTX01.xml</carfilename>
    </AEI_Report_UnitData>
    <AEI_Report_UnitData>
      <equipmentype>Piggyback</equipmentype>
      <direction>Fwd</direction>
      <sequence>036</sequence>
      <roadname>RTTX</roadname>
      <unitnumber>104041</unitnumber>
      <isloaded>true</isloaded>
      <cargotons>45</cargotons>
      <hazmatPlacardIndex>0</hazmatPlacardIndex>
      <destinationtag>WSP</destinationtag>
      <cardefect>All_Ok</cardefect>
      <carfilename>R8_Pig_RTTX05.xml</carfilename>
    </AEI_Report_UnitData>
    <AEI_Report_UnitData>
      <equipmentype>Piggyback</equipmentype>
      <direction>Rev</direction>
      <sequence>037</sequence>
      <roadname>RTTX</roadname>
      <unitnumber>938337</unitnumber>
      <isloaded>true</isloaded>
      <cargotons>45</cargotons>
      <hazmatPlacardIndex>0</hazmatPlacardIndex>
      <destinationtag>WSP</destinationtag>
      <cardefect>All_Ok</cardefect>
      <carfilename>R8_Pig_RTTX01.xml</carfilename>
    </AEI_Report_UnitData>
    <AEI_Report_UnitData>
      <equipmentype>Piggyback</equipmentype>
      <direction>Rev</direction>
      <sequence>038</sequence>
      <roadname>RTTX</roadname>
      <unitnumber>622745</unitnumber>
      <isloaded>true</isloaded>
      <cargotons>45</cargotons>
      <hazmatPlacardIndex>0</hazmatPlacardIndex>
      <destinationtag>WSP</destinationtag>
      <cardefect>All_Ok</cardefect>
      <carfilename>R8_Pig_RTTX05.xml</carfilename>
    </AEI_Report_UnitData>
    <AEI_Report_UnitData>
      <equipmentype>Piggyback</equipmentype>
      <direction>Fwd</direction>
      <sequence>039</sequence>
      <roadname>RTTX</roadname>
      <unitnumber>800556</unitnumber>
      <isloaded>true</isloaded>
      <cargotons>45</cargotons>
      <hazmatPlacardIndex>0</hazmatPlacardIndex>
      <destinationtag>WSP</destinationtag>
      <cardefect>All_Ok</cardefect>
      <carfilename>R8_Pig_RTTX06.xml</carfilename>
    </AEI_Report_UnitData>
    <AEI_Report_UnitData>
      <equipmentype>Piggyback</equipmentype>
      <direction>Fwd</direction>
      <sequence>040</sequence>
      <roadname>RTTX</roadname>
      <unitnumber>449098</unitnumber>
      <isloaded>true</isloaded>
      <cargotons>45</cargotons>
      <hazmatPlacardIndex>0</hazmatPlacardIndex>
      <destinationtag>WSP</destinationtag>
      <cardefect>All_Ok</cardefect>
      <carfilename>R8_Pig_RTTX07.xml</carfilename>
    </AEI_Report_UnitData>
    <AEI_Report_UnitData>
      <equipmentype>Piggyback</equipmentype>
      <direction>Rev</direction>
      <sequence>041</sequence>
      <roadname>RTTX</roadname>
      <unitnumber>491058</unitnumber>
      <isloaded>true</isloaded>
      <cargotons>45</cargotons>
      <hazmatPlacardIndex>0</hazmatPlacardIndex>
      <destinationtag>WSP</destinationtag>
      <cardefect>All_Ok</cardefect>
      <carfilename>R8_Pig_RTTX05.xml</carfilename>
    </AEI_Report_UnitData>
    <AEI_Report_UnitData>
      <equipmentype>Piggyback</equipmentype>
      <direction>Rev</direction>
      <sequence>042</sequence>
      <roadname>RTTX</roadname>
      <unitnumber>384493</unitnumber>
      <isloaded>true</isloaded>
      <cargotons>45</cargotons>
      <hazmatPlacardIndex>0</hazmatPlacardIndex>
      <destinationtag>WSP</destinationtag>
      <cardefect>All_Ok</cardefect>
      <carfilename>R8_Pig_RTTX07.xml</carfilename>
    </AEI_Report_UnitData>
    <AEI_Report_UnitData>
      <equipmentype>Piggyback</equipmentype>
      <direction>Fwd</direction>
      <sequence>043</sequence>
      <roadname>RTTX</roadname>
      <unitnumber>475810</unitnumber>
      <isloaded>true</isloaded>
      <cargotons>45</cargotons>
      <hazmatPlacardIndex>0</hazmatPlacardIndex>
      <destinationtag>WSP</destinationtag>
      <cardefect>All_Ok</cardefect>
      <carfilename>R8_Pig_RTTX01.xml</carfilename>
    </AEI_Report_UnitData>
    <AEI_Report_UnitData>
      <equipmentype>Piggyback</equipmentype>
      <direction>Fwd</direction>
      <sequence>044</sequence>
      <roadname>RTTX</roadname>
      <unitnumber>934889</unitnumber>
      <isloaded>true</isloaded>
      <cargotons>45</cargotons>
      <hazmatPlacardIndex>0</hazmatPlacardIndex>
      <destinationtag>WSP</destinationtag>
      <cardefect>All_Ok</cardefect>
      <carfilename>R8_Pig_RTTX03.xml</carfilename>
    </AEI_Report_UnitData>
    <AEI_Report_UnitData>
      <equipmentype>Piggyback</equipmentype>
      <direction>Fwd</direction>
      <sequence>045</sequence>
      <roadname>RTTX</roadname>
      <unitnumber>226444</unitnumber>
      <isloaded>true</isloaded>
      <cargotons>45</cargotons>
      <hazmatPlacardIndex>0</hazmatPlacardIndex>
      <destinationtag>WSP</destinationtag>
      <cardefect>All_Ok</cardefect>
      <carfilename>R8_Pig_RTTX02.xml</carfilename>
    </AEI_Report_UnitData>
    <AEI_Report_UnitData>
      <equipmentype>Piggyback</equipmentype>
      <direction>Fwd</direction>
      <sequence>046</sequence>
      <roadname>RTTX</roadname>
      <unitnumber>697330</unitnumber>
      <isloaded>true</isloaded>
      <cargotons>45</cargotons>
      <hazmatPlacardIndex>0</hazmatPlacardIndex>
      <destinationtag>WSP</destinationtag>
      <cardefect>All_Ok</cardefect>
      <carfilename>R8_Pig_RTTX05.xml</carfilename>
    </AEI_Report_UnitData>
    <AEI_Report_UnitData>
      <equipmentype>Piggyback</equipmentype>
      <direction>Rev</direction>
      <sequence>047</sequence>
      <roadname>RTTX</roadname>
      <unitnumber>151367</unitnumber>
      <isloaded>true</isloaded>
      <cargotons>45</cargotons>
      <hazmatPlacardIndex>0</hazmatPlacardIndex>
      <destinationtag>WSP</destinationtag>
      <cardefect>All_Ok</cardefect>
      <carfilename>R8_Pig_RTTX07.xml</carfilename>
    </AEI_Report_UnitData>
    <AEI_Report_UnitData>
      <equipmentype>Piggyback</equipmentype>
      <direction>Rev</direction>
      <sequence>048</sequence>
      <roadname>RTTX</roadname>
      <unitnumber>179503</unitnumber>
      <isloaded>true</isloaded>
      <cargotons>45</cargotons>
      <hazmatPlacardIndex>0</hazmatPlacardIndex>
      <destinationtag>WSP</destinationtag>
      <cardefect>All_Ok</cardefect>
      <carfilename>R8_Pig_RTTX03.xml</carfilename>
    </AEI_Report_UnitData>
    <AEI_Report_UnitData>
      <equipmentype>Piggyback</equipmentype>
      <direction>Rev</direction>
      <sequence>049</sequence>
      <roadname>RTTX</roadname>
      <unitnumber>372053</unitnumber>
      <isloaded>true</isloaded>
      <cargotons>45</cargotons>
      <hazmatPlacardIndex>0</hazmatPlacardIndex>
      <destinationtag>WSP</destinationtag>
      <cardefect>All_Ok</cardefect>
      <carfilename>R8_Pig_RTTX01.xml</carfilename>
    </AEI_Report_UnitData>
    <AEI_Report_UnitData>
      <equipmentype>Piggyback</equipmentype>
      <direction>Fwd</direction>
      <sequence>050</sequence>
      <roadname>RTTX</roadname>
      <unitnumber>173600</unitnumber>
      <isloaded>true</isloaded>
      <cargotons>45</cargotons>
      <hazmatPlacardIndex>0</hazmatPlacardIndex>
      <destinationtag>WSP</destinationtag>
      <cardefect>All_Ok</cardefect>
      <carfilename>R8_Pig_RTTX06.xml</carfilename>
    </AEI_Report_UnitData>
    <AEI_Report_UnitData>
      <equipmentype>Piggyback</equipmentype>
      <direction>Fwd</direction>
      <sequence>051</sequence>
      <roadname>RTTX</roadname>
      <unitnumber>782847</unitnumber>
      <isloaded>true</isloaded>
      <cargotons>45</cargotons>
      <hazmatPlacardIndex>0</hazmatPlacardIndex>
      <destinationtag>WSP</destinationtag>
      <cardefect>All_Ok</cardefect>
      <carfilename>R8_Pig_RTTX06.xml</carfilename>
    </AEI_Report_UnitData>
    <AEI_Report_UnitData>
      <equipmentype>Piggyback</equipmentype>
      <direction>Fwd</direction>
      <sequence>052</sequence>
      <roadname>RTTX</roadname>
      <unitnumber>526665</unitnumber>
      <isloaded>true</isloaded>
      <cargotons>45</cargotons>
      <hazmatPlacardIndex>0</hazmatPlacardIndex>
      <destinationtag>WSP</destinationtag>
      <cardefect>All_Ok</cardefect>
      <carfilename>R8_Pig_RTTX05.xml</carfilename>
    </AEI_Report_UnitData>
    <AEI_Report_UnitData>
      <equipmentype>Piggyback</equipmentype>
      <direction>Fwd</direction>
      <sequence>053</sequence>
      <roadname>RTTX</roadname>
      <unitnumber>440965</unitnumber>
      <isloaded>true</isloaded>
      <cargotons>45</cargotons>
      <hazmatPlacardIndex>0</hazmatPlacardIndex>
      <destinationtag>WSP</destinationtag>
      <cardefect>All_Ok</cardefect>
      <carfilename>R8_Pig_RTTX06.xml</carfilename>
    </AEI_Report_UnitData>
  </reportdata>
</AEI_Report>